<annotation>
	<folder>Train</folder>
	<filename>533.jpg</filename>
	<path>D:\DeepLearning\Datasets\equipment dataset\Train\533.jpg</path>
	<source>
		<database>Unknown</database>
	</source>
	<size>
		<width>311</width>
		<height>162</height>
		<depth>3</depth>
	</size>
	<segmented>0</segmented>
	<object>
		<name>Scissor Lift</name>
		<pose>Unspecified</pose>
		<truncated>0</truncated>
		<difficult>0</difficult>
		<bndbox>
			<xmin>151</xmin>
			<ymin>44</ymin>
			<xmax>242</xmax>
			<ymax>155</ymax>
		</bndbox>
	</object>
</annotation>
